AUTHORS.rst
CHANGES.rst
CONTRIBUTING.rst
LICENSE
MANIFEST.in
Makefile
README.rst
pytest.ini
setup.cfg
setup.py
docs/administratorguide.rst
docs/authors.rst
docs/changes.rst
docs/conf.py
docs/contributing.rst
docs/developerguide.rst
docs/gettingstarted.rst
docs/index.rst
docs/introduction.rst
docs/license.rst
docs/requirements.txt
docs/userguide.rst
docs/_static/logo-reana.png
docs/_static/reana-architecture.png
docs/_static/setting-the-breakpoint.png
docs/_static/wdb-active-sessions.png
docs/_static/wdb-debugging-ui.png
reana/__init__.py
reana/cli.py
reana/version.py
reana.egg-info/PKG-INFO
reana.egg-info/SOURCES.txt
reana.egg-info/dependency_links.txt
reana.egg-info/entry_points.txt
reana.egg-info/not-zip-safe
reana.egg-info/requires.txt
reana.egg-info/top_level.txt
tests/conftest.py
tests/test_cli.py
tests/test_version.py